configcat
